pytilkit/__init__.py
pytilkit/clearScreen.py
pytilkit/crypted.py
pytilkit/jsoned.py
pytilkit/maths.py
pytilkit/sized.py
pytilkit_open_contrib-1.0.1.dist-info/LICENSE
pytilkit_open_contrib-1.0.1.dist-info/METADATA
pytilkit_open_contrib-1.0.1.dist-info/WHEEL
pytilkit_open_contrib-1.0.1.dist-info/top_level.txt
pytilkit_open_contrib-1.0.1.dist-info/RECORD
